index_view.py
ivav-0.0.2.dist-info/LICENSE
ivav-0.0.2.dist-info/METADATA
ivav-0.0.2.dist-info/WHEEL
ivav-0.0.2.dist-info/top_level.txt
ivav-0.0.2.dist-info/RECORD
