Metadata-Version: 2.1
Name: ivav
Version: 0.0.2
Summary: A quantum computer simulator
Home-page: https://github.com/Gopal-Dahale/ivav
Author: Gopal Ramesh Dahale
Author-email: dahalegopal27@gmail.com
License: UNKNOWN
Platform: UNKNOWN
Classifier: Programming Language :: Python :: 3
Classifier: Programming Language :: Python :: 3.6
Classifier: License :: OSI Approved :: MIT License
Classifier: Operating System :: OS Independent
License-File: LICENSE
Provides-Extra: dev
Requires-Dist: pytest (>=7.0.1) ; extra == 'dev'
Requires-Dist: check-manisfest (>=0.47) ; extra == 'dev'
Requires-Dist: yapf (>=0.32.0) ; extra == 'dev'
